tanat/__init__.py
tanat/__main__.py
tanat/cli.py
tanat/exception.py
tanat/version.py
tanat/clustering/__init__.py
tanat/clustering/cluster.py
tanat/clustering/clusterer.py
tanat/clustering/config.py
tanat/clustering/mixin/__init__.py
tanat/clustering/mixin/medoid.py
tanat/clustering/type/__init__.py
tanat/clustering/type/clara.py
tanat/clustering/type/hierarchical.py
tanat/clustering/type/kernels.py
tanat/clustering/type/pam.py
tanat/criterion/__init__.py
tanat/criterion/config.py
tanat/criterion/utils.py
tanat/criterion/base/__init__.py
tanat/criterion/base/applier.py
tanat/criterion/base/enum.py
tanat/criterion/base/exception.py
tanat/criterion/base/settings.py
tanat/criterion/decorator/__init__.py
tanat/criterion/decorator/entity.py
tanat/criterion/decorator/sequence.py
tanat/criterion/decorator/trajectory.py
tanat/criterion/entity/__init__.py
tanat/criterion/entity/config.py
tanat/criterion/entity/base/__init__.py
tanat/criterion/entity/base/applier.py
tanat/criterion/entity/base/exception.py
tanat/criterion/entity/type/__init__.py
tanat/criterion/entity/type/pattern/__init__.py
tanat/criterion/entity/type/pattern/applier.py
tanat/criterion/entity/type/query/__init__.py
tanat/criterion/entity/type/query/applier.py
tanat/criterion/entity/type/rank/__init__.py
tanat/criterion/entity/type/rank/applier.py
tanat/criterion/entity/type/rank/settings.py
tanat/criterion/entity/type/time/__init__.py
tanat/criterion/entity/type/time/applier.py
tanat/criterion/mixin/pattern/__init__.py
tanat/criterion/mixin/pattern/applier.py
tanat/criterion/mixin/pattern/enum.py
tanat/criterion/mixin/pattern/exception.py
tanat/criterion/mixin/pattern/settings.py
tanat/criterion/mixin/query/__init__.py
tanat/criterion/mixin/query/applier.py
tanat/criterion/mixin/query/settings.py
tanat/criterion/mixin/static/__init__.py
tanat/criterion/mixin/static/applier.py
tanat/criterion/mixin/static/settings.py
tanat/criterion/mixin/time/__init__.py
tanat/criterion/mixin/time/applier.py
tanat-0.9.0.dist-info/METADATA
tanat-0.9.0.dist-info/WHEEL
tanat-0.9.0.dist-info/licenses/LICENSE.txt
tanat-0.9.0.dist-info/RECORD
