Metadata-Version: 2.4
Name: TanaT
Version: 0.9.0
Summary: A library for temporal analysis of trajectories.
Project-URL: Homepage, https://gitlab.inria.fr/tanat/core/tanat
Project-URL: Source, https://gitlab.inria.fr/tanat/core/tanat.git
Project-URL: Documentation, https://tanat.gitlabpages.inria.fr/tanat
Project-URL: Issues, https://gitlab.inria.fr/tanat/core/tanat/-/issues
Author-email: Arnaud Duvermy <arnaud.duvermy@inria.fr>, Thomas Guyet <thomas.guyet@inria.fr>
License: MIT License
License-File: LICENSE.txt
Classifier: License :: OSI Approved :: MIT License
Classifier: Operating System :: OS Independent
Classifier: Programming Language :: Python :: 3
Requires-Python: >=3.9
Requires-Dist: matplotlib
Requires-Dist: numba
Requires-Dist: pandas
Requires-Dist: pypassist
Requires-Dist: pyyaml
Requires-Dist: scikit-learn
Requires-Dist: scikit-survival
Requires-Dist: sqlalchemy
Requires-Dist: tanat-cli-preset
Requires-Dist: tqdm
Requires-Dist: tseqmock
Provides-Extra: runner
Requires-Dist: dagster; extra == 'runner'
Requires-Dist: hydra-core; extra == 'runner'
Provides-Extra: test
Requires-Dist: pytest; extra == 'test'
Requires-Dist: pytest-cov; extra == 'test'
Requires-Dist: syrupy; extra == 'test'
